LICENSE
MANIFEST.in
README.md
pyproject.toml
setup.py
dev_anket_laiser.egg-info/PKG-INFO
dev_anket_laiser.egg-info/SOURCES.txt
dev_anket_laiser.egg-info/dependency_links.txt
dev_anket_laiser.egg-info/requires.txt
dev_anket_laiser.egg-info/top_level.txt
laiser/__init__.py
laiser/llm_methods.py
laiser/params.py
laiser/skill_extractor.py
laiser/utils.py
laiser/llm_models/gemini.py
laiser/llm_models/hugging_face_llm.py
laiser/llm_models/llm_router.py
laiser/llm_models/model_loader.py
laiser/public/combined.csv
laiser/public/esco_faiss_index.index