Metadata-Version: 2.4
Name: dev-anket-laiser
Version: 2.2.17
Summary: LAiSER (Leveraging Artificial Intelligence for Skill Extraction & Research) is a tool designed to help learners, educators, and employers extract and share trusted information about skills. It uses a fine-tuned language model to extract raw skill keywords from text, then aligns them with a predefined taxonomy. You can find more technical details in the project's paper.md and an overview in the README.md.
Home-page: https://github.com/LAiSER-Software/extract-module
Author: Satya Phanindra Kumar Kalaga, Prudhvi Chekuri, Bharat Khandelwal, Anket Patil
Author-email: phanindra.connect@gmail.com
Classifier: Programming Language :: Python :: 3
Classifier: License :: OSI Approved :: BSD License
Classifier: Operating System :: OS Independent
Requires-Python: >=3.9,<3.12
License-File: LICENSE
Requires-Dist: numpy<2.0.0,>=1.21.0
Requires-Dist: pandas==2.2.2
Requires-Dist: psutil<6.0.0,>=5.8.0
Requires-Dist: skillNer==1.0.3
Requires-Dist: scikit-learn<2.0.0,>=1.0.0
Requires-Dist: spacy<4.0.0,>=3.0.0
Requires-Dist: transformers<5.0.0,>=4.0.0
Requires-Dist: tokenizers<1.0.0,>=0.10.0
Requires-Dist: torch==2.6.0
Requires-Dist: ipython<8.0.0,>=7.0.0
Requires-Dist: python-dotenv<1.0.0,>=0.19.0
Requires-Dist: tqdm<5.0.0,>=4.62.0
Requires-Dist: sentence-transformers==4.1.0
Requires-Dist: faiss-cpu==1.11.0
Requires-Dist: google.generativeai
Provides-Extra: gpu
Requires-Dist: torch==2.6.0; extra == "gpu"
Requires-Dist: vllm<1.0.0,>=0.1.0; extra == "gpu"
Requires-Dist: bitsandbytes>=0.42.0; extra == "gpu"
Requires-Dist: accelerate; extra == "gpu"
Provides-Extra: cpu
Requires-Dist: skillNer==1.0.3; extra == "cpu"
Requires-Dist: spacy<4.0.0,>=3.0.0; extra == "cpu"
Dynamic: author
Dynamic: author-email
Dynamic: classifier
Dynamic: description
Dynamic: description-content-type
Dynamic: home-page
Dynamic: license-file
Dynamic: provides-extra
Dynamic: requires-dist
Dynamic: requires-python
Dynamic: summary
